{
  "Category": "US Equities - Factor & Thematic",
  "Asset Type": "Equities (Stocks)",
  "Tags": "-",
  "Return% 1Y": "12.11%",
  "Total Holdings": "266",
  "Perf Week": "-2.87%",
  "Sponsor": "First Trust",
  "ETF Type": "",
  "Return% 3Y": "19.95%",
  "AUM": "414.46M",
  "Perf Month": "-1.30%",
  "Fund Family": "",
  "Bond Type": "",
  "Return% 5Y": "14.30%",
  "NAV/sh": "",
  "Perf Quarter": "3.84%",
  "Index": "-",
  "Average Maturity": "",
  "Return% 10Y": "",
  "52W High": "39.23 -3.39%",
  "Perf Half Y": "20.55%",
  "Index Weighting": "",
  "Commodity Type": "",
  "Return% SI": "",
  "52W Low": "29.11 30.20%",
  "Perf YTD": "9.76%",
  "Active/Passive": "",
  "Quant Type": "",
  "Flows% 1M": "2.39%",
  "Volatility": "1.09% 0.70%",
  "Perf Year": "11.31%",
  "Dividend TTM": "0.27 (0.70%)",
  "ESG Type": "",
  "Flows% 3M": "21.25%",
  "ATR (14)": "0.32",
  "Perf 3Y": "66.46%",
  "Dividend Ex-Date": "Sep 25, 2025",
  "Dividend Type": "",
  "Sector/Theme": "",
  "Flows% YTD": "204.85%",
  "RSI (14)": "39.67",
  "Perf 5Y": "100.32%",
  "Dividend Gr. 3/5Y": "-11.16% 35.54%",
  "Structure Type": "",
  "Region": "",
  "Flows% 1Y": "",
  "Beta": "0.96",
  "Perf 10Y": "-",
  "Expense": "0.55%",
  "Growth/Value": "",
  "SMA20": "-1.88%",
  "Flows% 3Y": "",
  "Rel Volume": "1.46",
  "Prev Close": "38.83",
  "Inverse/Leveraged": "",
  "Market Cap": "",
  "SMA50": "-0.16%",
  "Flows% 5Y": "",
  "Avg Volume": "61.94K",
  "Price": "37.90",
  "IPO": "Dec 04, 2019",
  "Option/Short": "No / Yes",
  "SMA200": "6.51%",
  "Trades": "",
  "Volume": "90,710",
  "Change": "-2.40%",
  "Dividends": []
}