{
  "Category": "US Equities - Quant Strat",
  "Asset Type": "Equities (Stocks)",
  "Tags": "-",
  "Return% 1Y": "13.16%",
  "Total Holdings": "5",
  "Perf Week": "-1.50%",
  "Sponsor": "Innovator Management",
  "ETF Type": "",
  "Return% 3Y": "18.02%",
  "AUM": "216.06M",
  "Perf Month": "-0.43%",
  "Fund Family": "",
  "Bond Type": "",
  "Return% 5Y": "11.61%",
  "NAV/sh": "",
  "Perf Quarter": "3.95%",
  "Index": "SPDR S&P 500 ETF Trust",
  "Average Maturity": "",
  "Return% 10Y": "",
  "52W High": "49.22 -1.81%",
  "Perf Half Y": "19.72%",
  "Index Weighting": "",
  "Commodity Type": "",
  "Return% SI": "",
  "52W Low": "38.38 25.92%",
  "Perf YTD": "10.89%",
  "Active/Passive": "",
  "Quant Type": "",
  "Flows% 1M": "0.56%",
  "Volatility": "0.62% 0.44%",
  "Perf Year": "13.16%",
  "Dividend TTM": "-",
  "ESG Type": "",
  "Flows% 3M": "28.20%",
  "ATR (14)": "0.27",
  "Perf 3Y": "64.39%",
  "Dividend Ex-Date": "-",
  "Dividend Type": "",
  "Sector/Theme": "",
  "Flows% YTD": "8.12%",
  "RSI (14)": "42.66",
  "Perf 5Y": "74.78%",
  "Dividend Gr. 3/5Y": "- -",
  "Structure Type": "",
  "Region": "",
  "Flows% 1Y": "",
  "Beta": "0.69",
  "Perf 10Y": "-",
  "Expense": "0.79%",
  "Growth/Value": "",
  "SMA20": "-1.06%",
  "Flows% 3Y": "",
  "Rel Volume": "0.09",
  "Prev Close": "49.10",
  "Inverse/Leveraged": "",
  "Market Cap": "",
  "SMA50": "0.29%",
  "Flows% 5Y": "",
  "Avg Volume": "36.73K",
  "Price": "48.33",
  "IPO": "Aug 01, 2019",
  "Option/Short": "No / Yes",
  "SMA200": "7.38%",
  "Trades": "",
  "Volume": "3,338",
  "Change": "-1.57%",
  "Dividends": []
}