{
  "Index": "-",
  "P/E": "35.74",
  "EPS (ttm)": "15.57",
  "Insider Own": "0.48%",
  "Shs Outstand": "37.18M",
  "Perf Week": "-1.90%",
  "Market Cap": "20.70B",
  "Forward P/E": "30.41",
  "EPS next Y": "11.34%",
  "Insider Trans": "-23.54%",
  "Shs Float": "37.00M",
  "Perf Month": "0.48%",
  "Enterprise Value": "23.13B",
  "PEG": "2.81",
  "EPS next Q": "5.15",
  "Inst Own": "89.20%",
  "Short Float": "1.70%",
  "Perf Quarter": "6.38%",
  "Income": "581.68M",
  "P/S": "1.26",
  "EPS this Y": "12.28%",
  "Inst Trans": "-3.15%",
  "Short Ratio": "2.01",
  "Perf Half Y": "27.09%",
  "Sales": "16.41B",
  "P/B": "5.69",
  "ROA": "7.82%",
  "Short Interest": "1.70%",
  "Perf YTD": "40.49%",
  "Book/sh": "97.92",
  "P/C": "45.18",
  "EPS next 5Y": "12.74%",
  "ROE": "17.10%",
  "52W High": "571.57 -2.61%",
  "Perf Year": "46.21%",
  "Cash/sh": "12.32",
  "P/FCF": "31.34",
  "EPS past 3/5Y": "17.18% 15.58%",
  "ROIC": "9.04%",
  "52W Low": "372.08 49.61%",
  "Perf 3Y": "174.56%",
  "Dividend Est.": "2.32 (0.42%)",
  "EV/EBITDA": "18.18",
  "Sales past 3/5Y": "7.16% 11.68%",
  "Gross Margin": "21.28%",
  "Volatility": "1.88% 2.06%",
  "Perf 5Y": "202.85%",
  "Dividend TTM": "2.07 (0.37%)",
  "EV/Sales": "1.41",
  "EPS Y/Y TTM": "13.37%",
  "Oper. Margin": "5.21%",
  "ATR (14)": "11.28",
  "Perf 10Y": "434.49%",
  "Dividend Ex-Date": "Oct 31, 2025",
  "Quick Ratio": "0.61",
  "Sales Y/Y TTM": "8.74%",
  "Profit Margin": "3.54%",
  "RSI (14)": "57.86",
  "Recom": "1.80",
  "Dividend Gr. 3/5Y": "12.89% 9.34%",
  "Current Ratio": "1.03",
  "EPS Q/Q": "19.27%",
  "SMA20": "0.40%",
  "Beta": "0.67",
  "Target Price": "582.67",
  "Payout": "13.67%",
  "Debt/Eq": "0.79",
  "Sales Q/Q": "11.45%",
  "SMA50": "4.99%",
  "Rel Volume": "0.56",
  "Prev Close": "552.24",
  "Employees": "49272",
  "LT Debt/Eq": "0.77",
  "Earnings": "Sep 08 AMC",
  "SMA200": "19.05%",
  "Avg Volume": "312.94K",
  "Price": "556.67",
  "IPO": "Oct 20, 1983",
  "Option/Short": "Yes / Yes",
  "EPS/Sales Surpr.": "14.99% 2.33%",
  "Trades": "",
  "Volume": "176,694",
  "Change": "0.80%",
  "Insider Trading": [
    {
      "Owner": "FRAZELL CHAD MICHAEL",
      "Relationship": "Chief HR Officer",
      "Date": "Sep 29 '25",
      "Transaction": "Sale",
      "Cost": "555.40",
      "Shares": "3,487",
      "Value": "1,936,680"
    },
    {
      "Owner": "FRAZELL CHAD MICHAEL",
      "Relationship": "Officer",
      "Date": "Sep 29 '25",
      "Transaction": "Proposed Sale",
      "Cost": "555.40",
      "Shares": "3,487",
      "Value": "1,936,687"
    },
    {
      "Owner": "Spanos Mike",
      "Relationship": "Director",
      "Date": "Sep 03 '25",
      "Transaction": "Option Exercise",
      "Cost": "0.00",
      "Shares": "442",
      "Value": "0"
    },
    {
      "Owner": "Wing Allison M.",
      "Relationship": "Director",
      "Date": "Sep 03 '25",
      "Transaction": "Option Exercise",
      "Cost": "0.00",
      "Shares": "442",
      "Value": "0"
    },
    {
      "Owner": "RENDA LARREE M",
      "Relationship": "Director",
      "Date": "Sep 03 '25",
      "Transaction": "Option Exercise",
      "Cost": "0.00",
      "Shares": "442",
      "Value": "0"
    },
    {
      "Owner": "Donthi Sri",
      "Relationship": "Director",
      "Date": "Sep 03 '25",
      "Transaction": "Option Exercise",
      "Cost": "0.00",
      "Shares": "442",
      "Value": "0"
    },
    {
      "Owner": "Trojan Greg",
      "Relationship": "Director",
      "Date": "Sep 03 '25",
      "Transaction": "Option Exercise",
      "Cost": "0.00",
      "Shares": "442",
      "Value": "0"
    },
    {
      "Owner": "LENHARDT DAVID K",
      "Relationship": "Director",
      "Date": "Sep 03 '25",
      "Transaction": "Option Exercise",
      "Cost": "0.00",
      "Shares": "442",
      "Value": "0"
    },
    {
      "Owner": "Castanon Moats Maria",
      "Relationship": "Director",
      "Date": "Sep 03 '25",
      "Transaction": "Option Exercise",
      "Cost": "0.00",
      "Shares": "442",
      "Value": "0"
    },
    {
      "Owner": "SCHMELING JUDY",
      "Relationship": "Director",
      "Date": "Sep 03 '25",
      "Transaction": "Option Exercise",
      "Cost": "0.00",
      "Shares": "442",
      "Value": "0"
    },
    {
      "Owner": "Frieson Donald",
      "Relationship": "Director",
      "Date": "Sep 03 '25",
      "Transaction": "Option Exercise",
      "Cost": "0.00",
      "Shares": "442",
      "Value": "0"
    },
    {
      "Owner": "Heiden Cara Kay",
      "Relationship": "Director",
      "Date": "Sep 03 '25",
      "Transaction": "Option Exercise",
      "Cost": "0.00",
      "Shares": "442",
      "Value": "0"
    },
    {
      "Owner": "Bramlage Stephen P JR",
      "Relationship": "Chief Financial Officer",
      "Date": "Jul 02 '25",
      "Transaction": "Sale",
      "Cost": "507.56",
      "Shares": "760",
      "Value": "385,746"
    },
    {
      "Owner": "Bramlage Stephen P JR",
      "Relationship": "Officer",
      "Date": "Jul 02 '25",
      "Transaction": "Proposed Sale",
      "Cost": "507.56",
      "Shares": "760",
      "Value": "385,746"
    },
    {
      "Owner": "Spanos Mike",
      "Relationship": "Director",
      "Date": "Jun 30 '25",
      "Transaction": "Buy",
      "Cost": "503.18",
      "Shares": "200",
      "Value": "100,636"
    },
    {
      "Owner": "Lindsey Katrina S",
      "Relationship": "Chief Legal Officer",
      "Date": "Jun 17 '25",
      "Transaction": "Sale",
      "Cost": "506.07",
      "Shares": "2,000",
      "Value": "1,012,140"
    },
    {
      "Owner": "REBELEZ DARREN M",
      "Relationship": "President and CEO",
      "Date": "Jun 17 '25",
      "Transaction": "Sale",
      "Cost": "507.83",
      "Shares": "20,000",
      "Value": "10,156,643"
    },
    {
      "Owner": "Koschel Williams Ena",
      "Relationship": "Chief Operating Officer",
      "Date": "Jun 17 '25",
      "Transaction": "Sale",
      "Cost": "507.97",
      "Shares": "8,000",
      "Value": "4,063,748"
    },
    {
      "Owner": "FRAZELL CHAD MICHAEL",
      "Relationship": "Chief HR Officer",
      "Date": "Jun 17 '25",
      "Transaction": "Sale",
      "Cost": "503.97",
      "Shares": "4,808",
      "Value": "2,423,110"
    },
    {
      "Owner": "Bramlage Stephen P JR",
      "Relationship": "Chief Financial Officer",
      "Date": "Jun 17 '25",
      "Transaction": "Sale",
      "Cost": "509.21",
      "Shares": "8,478",
      "Value": "4,317,046"
    },
    {
      "Owner": "Bramlage Stephen P JR",
      "Relationship": "Chief Financial Officer",
      "Date": "Jun 15 '25",
      "Transaction": "Option Exercise",
      "Cost": "0.00",
      "Shares": "1,826",
      "Value": "0"
    },
    {
      "Owner": "Brennan Thomas P JR",
      "Relationship": "Chief Merch. Officer",
      "Date": "Jun 15 '25",
      "Transaction": "Option Exercise",
      "Cost": "0.00",
      "Shares": "1,158",
      "Value": "0"
    },
    {
      "Owner": "FRAZELL CHAD MICHAEL",
      "Relationship": "Chief HR Officer",
      "Date": "Jun 15 '25",
      "Transaction": "Option Exercise",
      "Cost": "0.00",
      "Shares": "909",
      "Value": "0"
    },
    {
      "Owner": "Koschel Williams Ena",
      "Relationship": "Chief Operating Officer",
      "Date": "Jun 15 '25",
      "Transaction": "Option Exercise",
      "Cost": "0.00",
      "Shares": "1,948",
      "Value": "0"
    },
    {
      "Owner": "Lindsey Katrina S",
      "Relationship": "Chief Legal Officer",
      "Date": "Jun 15 '25",
      "Transaction": "Option Exercise",
      "Cost": "0.00",
      "Shares": "846",
      "Value": "0"
    },
    {
      "Owner": "REBELEZ DARREN M",
      "Relationship": "President and CEO",
      "Date": "Jun 15 '25",
      "Transaction": "Option Exercise",
      "Cost": "0.00",
      "Shares": "6,799",
      "Value": "0"
    },
    {
      "Owner": "Koschel Williams Ena",
      "Relationship": "Officer",
      "Date": "Jun 17 '25",
      "Transaction": "Proposed Sale",
      "Cost": "505.74",
      "Shares": "8,000",
      "Value": "4,045,920"
    },
    {
      "Owner": "Bramlage Stephen P JR",
      "Relationship": "Officer",
      "Date": "Jun 17 '25",
      "Transaction": "Proposed Sale",
      "Cost": "509.21",
      "Shares": "8,478",
      "Value": "4,317,074"
    },
    {
      "Owner": "REBELEZ DARREN M",
      "Relationship": "Officer",
      "Date": "Jun 17 '25",
      "Transaction": "Proposed Sale",
      "Cost": "505.74",
      "Shares": "20,000",
      "Value": "10,114,800"
    },
    {
      "Owner": "FRAZELL CHAD MICHAEL",
      "Relationship": "Officer",
      "Date": "Jun 17 '25",
      "Transaction": "Proposed Sale",
      "Cost": "503.97",
      "Shares": "4,808",
      "Value": "2,423,111"
    },
    {
      "Owner": "Lindsey Katrina S",
      "Relationship": "Officer",
      "Date": "Jun 17 '25",
      "Transaction": "Proposed Sale",
      "Cost": "506.07",
      "Shares": "2,000",
      "Value": "1,012,137"
    },
    {
      "Owner": "Brennan Thomas P JR",
      "Relationship": "Chief Merch. Officer",
      "Date": "Jun 16 '25",
      "Transaction": "Sale",
      "Cost": "506.03",
      "Shares": "6,600",
      "Value": "3,339,798"
    },
    {
      "Owner": "Wing Allison M.",
      "Relationship": "Director",
      "Date": "Jun 12 '25",
      "Transaction": "Sale",
      "Cost": "502.16",
      "Shares": "1,000",
      "Value": "502,160"
    },
    {
      "Owner": "Wing Allison M.",
      "Relationship": "Director",
      "Date": "Jun 12 '25",
      "Transaction": "Proposed Sale",
      "Cost": "502.16",
      "Shares": "1,000",
      "Value": "502,158"
    },
    {
      "Owner": "Lindsey Katrina S",
      "Relationship": "Chief Legal Officer",
      "Date": "Apr 04 '25",
      "Transaction": "Sale",
      "Cost": "437.01",
      "Shares": "250",
      "Value": "109,251"
    },
    {
      "Owner": "Katrina S. Lindsey",
      "Relationship": "Officer",
      "Date": "Apr 04 '25",
      "Transaction": "Proposed Sale",
      "Cost": "449.17",
      "Shares": "250",
      "Value": "112,292"
    },
    {
      "Owner": "RENDA LARREE M",
      "Relationship": "Director",
      "Date": "Mar 26 '25",
      "Transaction": "Sale",
      "Cost": "421.88",
      "Shares": "4,762",
      "Value": "2,008,993"
    },
    {
      "Owner": "RENDA LARREE M",
      "Relationship": "Director",
      "Date": "Mar 21 '25",
      "Transaction": "Proposed Sale",
      "Cost": "420.00",
      "Shares": "4,762",
      "Value": "2,000,040"
    },
    {
      "Owner": "Spanos Mike",
      "Relationship": "Director",
      "Date": "Mar 13 '25",
      "Transaction": "Buy",
      "Cost": "390.54",
      "Shares": "256",
      "Value": "99,978"
    },
    {
      "Owner": "Lindsey Katrina S",
      "Relationship": "Chief Legal Officer",
      "Date": "Mar 02 '25",
      "Transaction": "Option Exercise",
      "Cost": "0.00",
      "Shares": "102",
      "Value": "0"
    },
    {
      "Owner": "Lindsey Katrina S",
      "Relationship": "Chief Legal Officer",
      "Date": "Jan 03 '25",
      "Transaction": "Option Exercise",
      "Cost": "0.00",
      "Shares": "716",
      "Value": "0"
    },
    {
      "Owner": "Spanos Mike",
      "Relationship": "Director",
      "Date": "Dec 23 '24",
      "Transaction": "Buy",
      "Cost": "396.76",
      "Shares": "500",
      "Value": "198,380"
    },
    {
      "Owner": "Lindsey Katrina S",
      "Relationship": "Chief Legal Officer",
      "Date": "Dec 12 '24",
      "Transaction": "Sale",
      "Cost": "427.13",
      "Shares": "450",
      "Value": "192,208"
    },
    {
      "Owner": "Katrina S. Lindsey",
      "Relationship": "Officer",
      "Date": "Dec 12 '24",
      "Transaction": "Proposed Sale",
      "Cost": "427.81",
      "Shares": "450",
      "Value": "192,514"
    }
  ],
  "Dividends": []
}