{
  "Index": "RUT",
  "P/E": "19.03",
  "EPS (ttm)": "0.51",
  "Insider Own": "63.96%",
  "Shs Outstand": "53.86M",
  "Perf Week": "-12.87%",
  "Market Cap": "1.35B",
  "Forward P/E": "18.92",
  "EPS next Y": "11.51%",
  "Insider Trans": "0.00%",
  "Shs Float": "50.81M",
  "Perf Month": "-14.50%",
  "Enterprise Value": "1.67B",
  "PEG": "2.83",
  "EPS next Q": "0.08",
  "Inst Own": "42.60%",
  "Short Float": "8.43%",
  "Perf Quarter": "9.33%",
  "Income": "71.17M",
  "P/S": "1.01",
  "EPS this Y": "-5.39%",
  "Inst Trans": "0.09%",
  "Short Ratio": "2.09",
  "Perf Half Y": "20.28%",
  "Sales": "1.34B",
  "P/B": "3.51",
  "ROA": "5.70%",
  "Short Interest": "8.43%",
  "Perf YTD": "2.23%",
  "Book/sh": "2.74",
  "P/C": "5.68",
  "EPS next 5Y": "6.72%",
  "ROE": "20.48%",
  "52W High": "13.02 -26.16%",
  "Perf Year": "-9.51%",
  "Cash/sh": "1.69",
  "P/FCF": "23.60",
  "EPS past 3/5Y": "46.74% 42.51%",
  "ROIC": "8.09%",
  "52W Low": "6.61 45.39%",
  "Perf 3Y": "32.95%",
  "Dividend Est.": "-",
  "EV/EBITDA": "9.58",
  "Sales past 3/5Y": "16.84% 20.78%",
  "Gross Margin": "39.16%",
  "Volatility": "4.98% 4.25%",
  "Perf 5Y": "-",
  "Dividend TTM": "-",
  "EV/Sales": "1.25",
  "EPS Y/Y TTM": "-19.79%",
  "Oper. Margin": "6.76%",
  "ATR (14)": "0.46",
  "Perf 10Y": "-",
  "Dividend Ex-Date": "Mar 20, 2024",
  "Quick Ratio": "0.61",
  "Sales Y/Y TTM": "4.76%",
  "Profit Margin": "5.33%",
  "RSI (14)": "32.14",
  "Recom": "2.40",
  "Dividend Gr. 3/5Y": "- -",
  "Current Ratio": "1.33",
  "EPS Q/Q": "57.41%",
  "SMA20": "-10.50%",
  "Beta": "2.54",
  "Target Price": "12.08",
  "Payout": "0.00%",
  "Debt/Eq": "1.43",
  "Sales Q/Q": "15.70%",
  "SMA50": "-13.86%",
  "Rel Volume": "0.95",
  "Prev Close": "10.19",
  "Employees": "2550",
  "LT Debt/Eq": "1.28",
  "Earnings": "Aug 07 BMO",
  "SMA200": "-2.59%",
  "Avg Volume": "2.05M",
  "Price": "9.61",
  "IPO": "Nov 04, 2021",
  "Option/Short": "Yes / Yes",
  "EPS/Sales Surpr.": "67.00% 7.41%",
  "Trades": "",
  "Volume": "1,953,286",
  "Change": "-5.69%",
  "Insider Trading": [
    {
      "Owner": "Sedor Christian",
      "Relationship": "Chief Accounting Officer",
      "Date": "Aug 02 '25",
      "Transaction": "Option Exercise",
      "Cost": "0.00",
      "Shares": "1,000",
      "Value": "0"
    },
    {
      "Owner": "Porter Jennifer E",
      "Relationship": "Chief Marketing Officer",
      "Date": "Aug 02 '25",
      "Transaction": "Option Exercise",
      "Cost": "0.00",
      "Shares": "4,166",
      "Value": "0"
    },
    {
      "Owner": "VELTRI KATHY E",
      "Relationship": "Chief Retail Officer",
      "Date": "Aug 02 '25",
      "Transaction": "Option Exercise",
      "Cost": "0.00",
      "Shares": "4,166",
      "Value": "0"
    },
    {
      "Owner": "LEWIS GARY L",
      "Relationship": "Director",
      "Date": "May 16 '25",
      "Transaction": "Option Exercise",
      "Cost": "0.00",
      "Shares": "6,700",
      "Value": "0"
    },
    {
      "Owner": "DePree Alexis",
      "Relationship": "Director",
      "Date": "May 16 '25",
      "Transaction": "Option Exercise",
      "Cost": "0.00",
      "Shares": "6,700",
      "Value": "0"
    },
    {
      "Owner": "ADAMS ALBERT T",
      "Relationship": "Director",
      "Date": "May 16 '25",
      "Transaction": "Option Exercise",
      "Cost": "0.00",
      "Shares": "6,700",
      "Value": "0"
    },
    {
      "Owner": "Beargie William",
      "Relationship": "Director",
      "Date": "May 16 '25",
      "Transaction": "Option Exercise",
      "Cost": "0.00",
      "Shares": "6,700",
      "Value": "0"
    },
    {
      "Owner": "Hyde Andrea",
      "Relationship": "Director",
      "Date": "May 16 '25",
      "Transaction": "Option Exercise",
      "Cost": "0.00",
      "Shares": "6,700",
      "Value": "0"
    },
    {
      "Owner": "Burgdoerfer Stuart B",
      "Relationship": "Director",
      "Date": "May 16 '25",
      "Transaction": "Option Exercise",
      "Cost": "0.00",
      "Shares": "6,954",
      "Value": "0"
    },
    {
      "Owner": "Doody Alton F III",
      "Relationship": "Director",
      "Date": "May 16 '25",
      "Transaction": "Option Exercise",
      "Cost": "0.00",
      "Shares": "6,700",
      "Value": "0"
    },
    {
      "Owner": "KYEES JOHN E",
      "Relationship": "Director",
      "Date": "May 16 '25",
      "Transaction": "Option Exercise",
      "Cost": "0.00",
      "Shares": "6,700",
      "Value": "0"
    },
    {
      "Owner": "Chi Lisa",
      "Relationship": "Chief Merchandising Officer",
      "Date": "Apr 12 '25",
      "Transaction": "Option Exercise",
      "Cost": "0.00",
      "Shares": "1,513",
      "Value": "0"
    },
    {
      "Owner": "Porter Jennifer E",
      "Relationship": "Chief Marketing Officer",
      "Date": "Apr 12 '25",
      "Transaction": "Option Exercise",
      "Cost": "0.00",
      "Shares": "1,513",
      "Value": "0"
    },
    {
      "Owner": "VELTRI KATHY E",
      "Relationship": "Chief Retail Officer",
      "Date": "Apr 12 '25",
      "Transaction": "Option Exercise",
      "Cost": "0.00",
      "Shares": "1,513",
      "Value": "0"
    },
    {
      "Owner": "Sedor Christian",
      "Relationship": "Chief Accounting Officer",
      "Date": "Apr 12 '25",
      "Transaction": "Option Exercise",
      "Cost": "0.00",
      "Shares": "908",
      "Value": "0"
    },
    {
      "Owner": "Nachiappan Venkatachalam",
      "Relationship": "Chief Information Officer",
      "Date": "Apr 12 '25",
      "Transaction": "Option Exercise",
      "Cost": "0.00",
      "Shares": "1,513",
      "Value": "0"
    },
    {
      "Owner": "Sedor Christian",
      "Relationship": "Chief Accounting Officer",
      "Date": "Mar 19 '25",
      "Transaction": "Option Exercise",
      "Cost": "0.00",
      "Shares": "1,103",
      "Value": "0"
    },
    {
      "Owner": "Chi Lisa",
      "Relationship": "Chief Merchandising Officer",
      "Date": "Mar 19 '25",
      "Transaction": "Option Exercise",
      "Cost": "0.00",
      "Shares": "41,352",
      "Value": "0"
    },
    {
      "Owner": "Nachiappan Venkatachalam",
      "Relationship": "Chief Information Officer",
      "Date": "Mar 19 '25",
      "Transaction": "Option Exercise",
      "Cost": "0.00",
      "Shares": "33,081",
      "Value": "0"
    },
    {
      "Owner": "Porter Jennifer E",
      "Relationship": "Chief Marketing Officer",
      "Date": "Mar 19 '25",
      "Transaction": "Option Exercise",
      "Cost": "0.00",
      "Shares": "41,352",
      "Value": "0"
    },
    {
      "Owner": "VELTRI KATHY E",
      "Relationship": "Chief Retail Officer",
      "Date": "Mar 19 '25",
      "Transaction": "Option Exercise",
      "Cost": "0.00",
      "Shares": "41,352",
      "Value": "0"
    },
    {
      "Owner": "Sedor Christian",
      "Relationship": "Chief Accounting Officer",
      "Date": "Mar 10 '25",
      "Transaction": "Option Exercise",
      "Cost": "0.00",
      "Shares": "855",
      "Value": "0"
    },
    {
      "Owner": "Porter Jennifer E",
      "Relationship": "Chief Marketing Officer",
      "Date": "Mar 10 '25",
      "Transaction": "Option Exercise",
      "Cost": "0.00",
      "Shares": "2,340",
      "Value": "0"
    },
    {
      "Owner": "VELTRI KATHY E",
      "Relationship": "Chief Retail Officer",
      "Date": "Mar 10 '25",
      "Transaction": "Option Exercise",
      "Cost": "0.00",
      "Shares": "2,340",
      "Value": "0"
    },
    {
      "Owner": "Nachiappan Venkatachalam",
      "Relationship": "Chief Information Officer",
      "Date": "Mar 10 '25",
      "Transaction": "Option Exercise",
      "Cost": "0.00",
      "Shares": "1,872",
      "Value": "0"
    },
    {
      "Owner": "Chi Lisa",
      "Relationship": "Chief Merchandising Officer",
      "Date": "Mar 10 '25",
      "Transaction": "Option Exercise",
      "Cost": "0.00",
      "Shares": "2,340",
      "Value": "0"
    },
    {
      "Owner": "Chi Lisa",
      "Relationship": "Chief Merchandising Officer",
      "Date": "Nov 09 '24",
      "Transaction": "Option Exercise",
      "Cost": "0.00",
      "Shares": "50,000",
      "Value": "0"
    },
    {
      "Owner": "Phillipson Dawn",
      "Relationship": "Chief Financial Officer",
      "Date": "Nov 09 '24",
      "Transaction": "Option Exercise",
      "Cost": "0.00",
      "Shares": "16,667",
      "Value": "0"
    },
    {
      "Owner": "VELTRI KATHY E",
      "Relationship": "Chief Retail Officer",
      "Date": "Nov 09 '24",
      "Transaction": "Option Exercise",
      "Cost": "0.00",
      "Shares": "16,667",
      "Value": "0"
    },
    {
      "Owner": "Porter Jennifer E",
      "Relationship": "Chief Marketing Officer",
      "Date": "Nov 09 '24",
      "Transaction": "Option Exercise",
      "Cost": "0.00",
      "Shares": "16,667",
      "Value": "0"
    },
    {
      "Owner": "Nachiappan Venkatachalam",
      "Relationship": "Chief Information Officer",
      "Date": "Nov 09 '24",
      "Transaction": "Option Exercise",
      "Cost": "0.00",
      "Shares": "50,000",
      "Value": "0"
    }
  ],
  "Dividends": []
}