{
  "Index": "RUT",
  "P/E": "33.83",
  "EPS (ttm)": "4.07",
  "Insider Own": "16.95%",
  "Shs Outstand": "10.55M",
  "Perf Week": "-0.89%",
  "Market Cap": "1.69B",
  "Forward P/E": "20.72",
  "EPS next Y": "7.51%",
  "Insider Trans": "-0.66%",
  "Shs Float": "10.27M",
  "Perf Month": "-7.14%",
  "Enterprise Value": "1.99B",
  "PEG": "2.48",
  "EPS next Q": "1.61",
  "Inst Own": "78.64%",
  "Short Float": "3.40%",
  "Perf Quarter": "35.48%",
  "Income": "50.15M",
  "P/S": "2.84",
  "EPS this Y": "7.14%",
  "Inst Trans": "-",
  "Short Ratio": "2.48",
  "Perf Half Y": "106.28%",
  "Sales": "594.03M",
  "P/B": "4.21",
  "ROA": "6.72%",
  "Short Interest": "3.40%",
  "Perf YTD": "67.01%",
  "Book/sh": "32.74",
  "P/C": "28.46",
  "EPS next 5Y": "13.65%",
  "ROE": "13.40%",
  "52W High": "152.45 -9.66%",
  "Perf Year": "70.33%",
  "Cash/sh": "4.84",
  "P/FCF": "35.63",
  "EPS past 3/5Y": "17.48% -",
  "ROIC": "7.44%",
  "52W Low": "57.99 137.49%",
  "Perf 3Y": "423.09%",
  "Dividend Est.": "-",
  "EV/EBITDA": "20.33",
  "Sales past 3/5Y": "-0.54% 1.66%",
  "Gross Margin": "37.84%",
  "Volatility": "4.56% 4.54%",
  "Perf 5Y": "1150.95%",
  "Dividend TTM": "0.35 (0.25%)",
  "EV/Sales": "3.34",
  "EPS Y/Y TTM": "-23.58%",
  "Oper. Margin": "12.65%",
  "ATR (14)": "6.18",
  "Perf 10Y": "612.52%",
  "Dividend Ex-Date": "Oct 15, 2025",
  "Quick Ratio": "1.72",
  "Sales Y/Y TTM": "6.08%",
  "Profit Margin": "8.44%",
  "RSI (14)": "45.74",
  "Recom": "1.17",
  "Dividend Gr. 3/5Y": "0.00% 0.00%",
  "Current Ratio": "3.05",
  "EPS Q/Q": "37.65%",
  "SMA20": "-3.98%",
  "Beta": "1.59",
  "Target Price": "147.50",
  "Payout": "8.42%",
  "Debt/Eq": "0.69",
  "Sales Q/Q": "26.35%",
  "SMA50": "-0.69%",
  "Rel Volume": "1.02",
  "Prev Close": "142.94",
  "Employees": "5370",
  "LT Debt/Eq": "0.67",
  "Earnings": "Jul 24 AMC",
  "SMA200": "43.04%",
  "Avg Volume": "141.07K",
  "Price": "137.73",
  "IPO": "Jul 10, 1998",
  "Option/Short": "Yes / Yes",
  "EPS/Sales Surpr.": "36.24% 11.50%",
  "Trades": "",
  "Volume": "143,545",
  "Change": "-3.64%",
  "Insider Trading": [
    {
      "Owner": "Lai Kenneth Koon Keung",
      "Relationship": "VP of Asia Operations",
      "Date": "Aug 01 '25",
      "Transaction": "Sale",
      "Cost": "128.00",
      "Shares": "1,900",
      "Value": "243,200"
    },
    {
      "Owner": "KOON KEUNG KENNETH LAI",
      "Relationship": "Officer",
      "Date": "Aug 01 '25",
      "Transaction": "Proposed Sale",
      "Cost": "128.00",
      "Shares": "1,900",
      "Value": "243,200"
    },
    {
      "Owner": "Dawson Stephen",
      "Relationship": "Pres. - Power Solutions",
      "Date": "Jul 31 '25",
      "Transaction": "Sale",
      "Cost": "127.07",
      "Shares": "1,200",
      "Value": "152,484"
    },
    {
      "Owner": "STEVE DAWSON",
      "Relationship": "Officer",
      "Date": "Jul 31 '25",
      "Transaction": "Proposed Sale",
      "Cost": "127.07",
      "Shares": "1,200",
      "Value": "152,484"
    },
    {
      "Owner": "Lai Kenneth Koon Keung",
      "Relationship": "VP of Asia Operations",
      "Date": "Jun 13 '25",
      "Transaction": "Sale",
      "Cost": "84.03",
      "Shares": "4,000",
      "Value": "336,120"
    },
    {
      "Owner": "KOON KEUNG KENNETH LAI",
      "Relationship": "Officer",
      "Date": "Jun 13 '25",
      "Transaction": "Proposed Sale",
      "Cost": "84.03",
      "Shares": "4,000",
      "Value": "336,110"
    },
    {
      "Owner": "BERNSTEIN DANIEL",
      "Relationship": "President and CEO",
      "Date": "Apr 30 '25",
      "Transaction": "Sale",
      "Cost": "65.82",
      "Shares": "6,652",
      "Value": "437,835"
    },
    {
      "Owner": "DANIEL BERNSTEIN",
      "Relationship": "Officer",
      "Date": "Apr 30 '25",
      "Transaction": "Proposed Sale",
      "Cost": "65.82",
      "Shares": "6,652",
      "Value": "437,833"
    },
    {
      "Owner": "Kozlovsky Suzanne",
      "Relationship": "Global Head of People",
      "Date": "Mar 17 '25",
      "Transaction": "Sale",
      "Cost": "75.91",
      "Shares": "194",
      "Value": "14,727"
    },
    {
      "Owner": "Berry Joseph Francis",
      "Relationship": "VP of Magnetic Solutions",
      "Date": "Nov 26 '24",
      "Transaction": "Sale",
      "Cost": "80.30",
      "Shares": "1,000",
      "Value": "80,300"
    },
    {
      "Owner": "Berry Joseph Francis",
      "Relationship": "Officer",
      "Date": "Nov 25 '24",
      "Transaction": "Proposed Sale",
      "Cost": "80.00",
      "Shares": "1,000",
      "Value": "80,000"
    },
    {
      "Owner": "Dawson Stephen",
      "Relationship": "Pres. - Power Solutions",
      "Date": "Nov 21 '24",
      "Transaction": "Sale",
      "Cost": "77.65",
      "Shares": "1,500",
      "Value": "116,475"
    },
    {
      "Owner": "Dawson Stephen",
      "Relationship": "Officer",
      "Date": "Nov 20 '24",
      "Transaction": "Proposed Sale",
      "Cost": "73.33",
      "Shares": "1,500",
      "Value": "110,000"
    }
  ],
  "Dividends": []
}