{
  "Category": "Target Date / Multi-Asset - Other",
  "Asset Type": "Multi-Asset - Growth / Aggressive",
  "Tags": "-",
  "Return% 1Y": "10.84%",
  "Total Holdings": "9",
  "Perf Week": "-1.72%",
  "Sponsor": "Blackrock (iShares)",
  "ETF Type": "",
  "Return% 3Y": "13.92%",
  "AUM": "2.79B",
  "Perf Month": "-0.91%",
  "Fund Family": "",
  "Bond Type": "",
  "Return% 5Y": "7.76%",
  "NAV/sh": "",
  "Perf Quarter": "3.66%",
  "Index": "S&P Target Risk Growth Index",
  "Average Maturity": "",
  "Return% 10Y": "",
  "52W High": "64.72 -1.99%",
  "Perf Half Y": "15.31%",
  "Index Weighting": "",
  "Commodity Type": "",
  "Return% SI": "",
  "52W Low": "52.97 19.75%",
  "Perf YTD": "10.66%",
  "Active/Passive": "",
  "Quant Type": "",
  "Flows% 1M": "1.52%",
  "Volatility": "0.67% 0.47%",
  "Perf Year": "8.37%",
  "Dividend TTM": "1.59 (2.51%)",
  "ESG Type": "",
  "Flows% 3M": "5.99%",
  "ATR (14)": "0.36",
  "Perf 3Y": "37.68%",
  "Dividend Ex-Date": "Oct 02, 2025",
  "Dividend Type": "",
  "Sector/Theme": "",
  "Flows% YTD": "3.78%",
  "RSI (14)": "41.84",
  "Perf 5Y": "30.35%",
  "Dividend Gr. 3/5Y": "17.70% 4.45%",
  "Structure Type": "",
  "Region": "",
  "Flows% 1Y": "",
  "Beta": "0.65",
  "Perf 10Y": "69.04%",
  "Expense": "0.15%",
  "Growth/Value": "",
  "SMA20": "-1.28%",
  "Flows% 3Y": "",
  "Rel Volume": "1.61",
  "Prev Close": "64.43",
  "Inverse/Leveraged": "",
  "Market Cap": "",
  "SMA50": "0.20%",
  "Flows% 5Y": "",
  "Avg Volume": "196.97K",
  "Price": "63.43",
  "IPO": "Nov 11, 2008",
  "Option/Short": "Yes / Yes",
  "SMA200": "5.92%",
  "Trades": "",
  "Volume": "318,029",
  "Change": "-1.55%",
  "Dividends": []
}