{
  "Index": "-",
  "P/E": "151.68",
  "EPS (ttm)": "0.22",
  "Insider Own": "0.00%",
  "Shs Outstand": "2.60B",
  "Perf Week": "-1.96%",
  "Market Cap": "86.14B",
  "Forward P/E": "11.64",
  "EPS next Y": "6.28%",
  "Insider Trans": "-",
  "Shs Float": "2.57B",
  "Perf Month": "-2.84%",
  "Enterprise Value": "146.35B",
  "PEG": "56.81",
  "EPS next Q": "0.74",
  "Inst Own": "12.55%",
  "Short Float": "0.33%",
  "Perf Quarter": "4.33%",
  "Income": "600.44M",
  "P/S": "0.46",
  "EPS this Y": "-17.05%",
  "Inst Trans": "792.21%",
  "Short Ratio": "1.19",
  "Perf Half Y": "27.68%",
  "Sales": "186.67B",
  "P/B": "1.47",
  "ROA": "0.22%",
  "Short Interest": "0.33%",
  "Perf YTD": "13.30%",
  "Book/sh": "22.79",
  "P/C": "2.44",
  "EPS next 5Y": "2.67%",
  "ROE": "0.95%",
  "52W High": "35.88 -6.66%",
  "Perf Year": "4.56%",
  "Cash/sh": "13.73",
  "P/FCF": "10.00",
  "EPS past 3/5Y": "-60.13% -34.56%",
  "ROIC": "0.48%",
  "52W Low": "25.22 32.77%",
  "Perf 3Y": "6.72%",
  "Dividend Est.": "1.97 (5.90%)",
  "EV/EBITDA": "4.58",
  "Sales past 3/5Y": "6.26% -7.43%",
  "Gross Margin": "15.83%",
  "Volatility": "1.68% 1.41%",
  "Perf 5Y": "94.82%",
  "Dividend TTM": "1.94 (5.79%)",
  "EV/Sales": "0.78",
  "EPS Y/Y TTM": "-90.89%",
  "Oper. Margin": "7.89%",
  "ATR (14)": "0.63",
  "Perf 10Y": "2.98%",
  "Dividend Ex-Date": "Aug 15, 2025",
  "Quick Ratio": "0.92",
  "Sales Y/Y TTM": "-7.40%",
  "Profit Margin": "0.32%",
  "RSI (14)": "40.92",
  "Recom": "2.35",
  "Dividend Gr. 3/5Y": "13.27% -5.44%",
  "Current Ratio": "1.21",
  "EPS Q/Q": "1435.76%",
  "SMA20": "-3.02%",
  "Beta": "0.48",
  "Target Price": "38.65",
  "Payout": "1298.95%",
  "Debt/Eq": "1.27",
  "Sales Q/Q": "-0.25%",
  "SMA50": "-2.46%",
  "Rel Volume": "1.06",
  "Prev Close": "34.29",
  "Employees": "100500",
  "LT Debt/Eq": "1.12",
  "Earnings": "Nov 04 BMO",
  "SMA200": "5.16%",
  "Avg Volume": "7.10M",
  "Price": "33.49",
  "IPO": "Jul 02, 1962",
  "Option/Short": "Yes / Yes",
  "EPS/Sales Surpr.": "0.00% 0.00%",
  "Trades": "",
  "Volume": "7,538,178",
  "Change": "-2.33%",
  "Dividends": []
}